get_random_samples_of_picture/LICENSE
get_random_samples_of_picture/README.MD
get_random_samples_of_picture/__init__.py
get_random_samples_of_picture/requirements.txt
get_random_samples_of_picture/thirdparty.json
get_random_samples_of_picture-0.10.dist-info/LICENSE.rst
get_random_samples_of_picture-0.10.dist-info/METADATA
get_random_samples_of_picture-0.10.dist-info/WHEEL
get_random_samples_of_picture-0.10.dist-info/top_level.txt
get_random_samples_of_picture-0.10.dist-info/RECORD
