Metadata-Version: 2.1
Name: get-random-samples-of-picture
Version: 0.10
Summary: Get samples from a picture
Home-page: https://github.com/hansalemaos/get_random_samples_of_picture
Author: Johannes Fischer
Author-email: <aulasparticularesdealemaosp@gmail.com>
License: MIT
Keywords: cv2,image,samples,crop
Classifier: Development Status :: 4 - Beta
Classifier: Programming Language :: Python :: 3 :: Only
Classifier: Programming Language :: Python :: 3.9
Classifier: Topic :: Scientific/Engineering :: Visualization
Classifier: Topic :: Software Development :: Libraries :: Python Modules
Classifier: Topic :: Text Editors :: Text Processing
Classifier: Topic :: Text Processing :: General
Classifier: Topic :: Text Processing :: Indexing
Classifier: Topic :: Text Processing :: Filters
Classifier: Topic :: Utilities
License-File: LICENSE.rst
Requires-Dist: a-cv2-easy-resize
Requires-Dist: a-cv-imwrite-imread-plus
Requires-Dist: opencv-python
